dialektos/__init__.py
dialektos-0.0.0.dist-info/METADATA
dialektos-0.0.0.dist-info/WHEEL
dialektos-0.0.0.dist-info/entry_points.txt
dialektos-0.0.0.dist-info/RECORD
