Metadata-Version: 2.4
Name: dialektos
Version: 0.0.0
Summary: Conversational AI
Author-email: Charalampos Mitsakis <c@mitsakis.org>
Requires-Python: >=3.13
Requires-Dist: litellm~=1.55
